issues/__init__.py
issues/apps.py
issues/checks.py
issues/config.py
issues/exceptions.py
issues/forms.py
issues/py.typed
issues/urls.py
issues/utils.py
issues/version.py
issues/views.py
issues/backends/__init__.py
issues/backends/_base.py
issues/backends/azure_devops.py
issues/backends/console.py
issues/backends/debug.py
issues/backends/email.py
issues/backends/github.py
issues/backends/github_repo.py
issues/backends/gitlab.py
issues/backends/taiga.py
issues/static/issues/axios.js
issues/static/issues/axios.min.js
issues/static/issues/dom-to-image.js
issues/static/issues/dom-to-image.min.js
issues/static/issues/html2canvas-pro.js
issues/static/issues/html2canvas-pro.min.js
issues/static/issues/html2canvas.js
issues/static/issues/html2canvas.min.js
issues/static/issues/issues.css
issues/static/issues/issues.css.map
issues/static/issues/issues.js
issues/static/issues/issues.min.js
issues/static/issues/issues.scss
issues/static/issues/rasterizeHTML.js
issues/static/issues/rasterizeHTML.min.js
issues/templates/issues/issue_form.html
issues/templatetags/__init__.py
issues/templatetags/issues.py
django_online_issues-0.6.dist-info/METADATA
django_online_issues-0.6.dist-info/WHEEL
django_online_issues-0.6.dist-info/licenses/LICENSE
django_online_issues-0.6.dist-info/RECORD
