Metadata-Version: 2.4
Name: django-online-issues
Version: 0.6
Summary: A reusable Django app for collecting and reporting user-submitted issues (tickets). It provides a view and a form to submit tickets and forwards them to configurable backends like GitLab, GitHub, email, or simply the development console.
Project-URL: Documentation, https://github.com/saxix/django-issues
Project-URL: Homepage, https://github.com/saxix/django-issues
Author-email: Stefano Apostolico <s.apostolico@gmail.com>
License-File: LICENSE
Classifier: Environment :: Web Environment
Classifier: Framework :: Django
Classifier: Framework :: Django :: 4.2
Classifier: Framework :: Django :: 5.2
Classifier: Intended Audience :: Developers
Classifier: License :: OSI Approved :: MIT License
Classifier: Operating System :: OS Independent
Classifier: Programming Language :: Python :: 3 :: Only
Classifier: Programming Language :: Python :: 3.9
Classifier: Programming Language :: Python :: 3.10
Classifier: Programming Language :: Python :: 3.11
Classifier: Programming Language :: Python :: 3.12
Classifier: Programming Language :: Python :: 3.13
Classifier: Topic :: Software Development :: Libraries :: Application Frameworks
Classifier: Topic :: Software Development :: Libraries :: Python Modules
Requires-Python: >=3.9
Requires-Dist: django-stubs-ext
Requires-Dist: django>=4
Requires-Dist: markdown>=3.8.2
Requires-Dist: requests>=2.32.5
Provides-Extra: github
Requires-Dist: pygithub>=2.8; extra == 'github'
Provides-Extra: gitlab
Requires-Dist: python-gitlab>=6.3; extra == 'gitlab'
